datafn/__init__.py
datafn/change_tracking.py
datafn/db.py
datafn/envelope.py
datafn/filters.py
datafn/guards.py
datafn/idempotency.py
datafn/relations.py
datafn/server.py
datafn/transaction.py
datafn/validation.py
datafn/handlers/mutation.py
datafn/handlers/query.py
datafn/handlers/sync.py
datafn/handlers/transact.py
datafn-0.0.1.dist-info/METADATA
datafn-0.0.1.dist-info/WHEEL
datafn-0.0.1.dist-info/RECORD
