Metadata-Version: 2.4
Name: datafn
Version: 0.0.1
Summary: Python Server SDK for DataFn
Requires-Python: >=3.8
